_jsonrpc/__init__.py
_jsonrpc/abc.py
_jsonrpc/executor.py
celestia/_celestia.cpython-313-x86_64-linux-gnu.so
celestia/node_api/__init__.py
celestia/node_api/blob.py
celestia/node_api/das.py
celestia/node_api/fraud.py
celestia/node_api/header.py
celestia/node_api/p2p.py
celestia/node_api/share.py
celestia/node_api/state.py
celestia/types/__init__.py
celestia/types/blob.py
celestia/types/common.py
celestia/types/das.py
celestia/types/header.py
celestia/types/p2p.py
celestia/types/rawshare.py
celestia/types/state.py
pycelestia-0.1.7.dist-info/METADATA
pycelestia-0.1.7.dist-info/WHEEL
pycelestia-0.1.7.dist-info/top_level.txt
pycelestia-0.1.7.dist-info/RECORD
