Metadata-Version: 2.4
Name: pyCelestia
Version: 0.1.7
Summary: The Python client for working with the Celestia blockchain platform.
License: MIT License
Project-URL: Homepage, https://github.com/Alesh/pyCelestia
Project-URL: Issues, https://github.com/Alesh/pyCelestia
Classifier: Programming Language :: Python :: 3
Classifier: License :: OSI Approved :: MIT License
Classifier: Operating System :: POSIX
Requires-Python: >=3.10
Requires-Dist: ajsonrpc
Requires-Dist: websockets
Requires-Dist: typing_extensions; python_version < "3.11"
Requires-Dist: async_timeout; python_version < "3.11"
Provides-Extra: test
Requires-Dist: pytest; extra == "test"
Requires-Dist: pytest-asyncio; extra == "test"
Requires-Dist: pydantic; extra == "test"
